flowtune/__init__.py
flowtune/executor.py
flowtune/parser.py
flowtune-1.2.0.dist-info/licenses/LICENSE
flowtune-1.2.0.dist-info/METADATA
flowtune-1.2.0.dist-info/WHEEL
flowtune-1.2.0.dist-info/top_level.txt
flowtune-1.2.0.dist-info/RECORD
