Metadata-Version: 2.4
Name: flowtune
Version: 1.2.0
Summary: Flowtune with auto configuration support
Home-page: https://github.com/zaminnes/flowtune
Author: zaminnes
Author-email: your.email@example.com
Classifier: Programming Language :: Python :: 3
Classifier: License :: OSI Approved :: MIT License
Requires-Python: >=3.7
License-File: LICENSE
Requires-Dist: requests
Dynamic: author
Dynamic: author-email
Dynamic: classifier
Dynamic: home-page
Dynamic: license-file
Dynamic: requires-dist
Dynamic: requires-python
Dynamic: summary
